README.md
setup.py
ravenml/__init__.py
ravenml/cli.py
ravenml/options.py
ravenml.egg-info/PKG-INFO
ravenml.egg-info/SOURCES.txt
ravenml.egg-info/dependency_links.txt
ravenml.egg-info/entry_points.txt
ravenml.egg-info/requires.txt
ravenml.egg-info/top_level.txt
ravenml/config/__init__.py
ravenml/config/commands.py
ravenml/data/__init__.py
ravenml/data/commands.py
ravenml/data/interfaces.py
ravenml/data/options.py
ravenml/train/__init__.py
ravenml/train/commands.py
ravenml/train/interfaces.py
ravenml/train/options.py
ravenml/utils/__init__.py
ravenml/utils/aws.py
ravenml/utils/config.py
ravenml/utils/dataset.py
ravenml/utils/imageset.py
ravenml/utils/local_cache.py
ravenml/utils/plugins.py
ravenml/utils/question.py