Metadata-Version: 2.1
Name: ravenml
Version: 1.2
Summary: ML Training CLI Tool
Home-page: UNKNOWN
Author: Carson Schubert, Abhi Dhir, Pratyush Singh
Author-email: carson.schubert14@gmail.com
License: MIT
Download-URL: https://github.com/autognc/ravenML/archive/v1.2.tar.gz
Keywords: machine learning,data science
Platform: UNKNOWN
